powheg_tools/__init__.py
powheg_tools/cleanpowheg/__init__.py
powheg_tools/find-outlier/find.py
powheg_tools/find-outlier/pwgevents-0001.lhe
powheg_tools/find-outlier/pwgevents-0001.lhe.zip
powheg_tools/geninitrwgt/__init__.py
powheg_tools/geninitrwgt/initrwgt.py
powheg_tools/genpwgseeds/__init__.py
powheg_tools/powheg_to_lhe_standard/powheg_to_lhe_standard.py
powheg_tools/rivet_pdf_rename/README.md
powheg_tools/rivet_pdf_rename/__init__.py
powheg_tools/rivet_pdf_rename/rename.py
powheg_tools/yoda_auc/README.md
powheg_tools/yoda_auc/__init__.py
powheg_tools/yoda_auc/auc.py
powheg_tools-0.2.7.dist-info/METADATA
powheg_tools-0.2.7.dist-info/WHEEL
powheg_tools-0.2.7.dist-info/entry_points.txt
powheg_tools-0.2.7.dist-info/RECORD
