Metadata-Version: 2.1
Name: powheg-tools
Version: 0.2.7
Summary: 
Author: Alexander Puck Neuwirth
Author-email: alexander@neuwirth-informatik.de
Requires-Python: >=3.8,<4.0
Classifier: Programming Language :: Python :: 3
Classifier: Programming Language :: Python :: 3.8
Classifier: Programming Language :: Python :: 3.9
Classifier: Programming Language :: Python :: 3.10
Classifier: Programming Language :: Python :: 3.11
Requires-Dist: pypowhegparse
Requires-Dist: pytopdrawer
Requires-Dist: scikit-learn
